LICENSE
README.md
setup.py
pylmkit/__init__.py
pylmkit.egg-info/PKG-INFO
pylmkit.egg-info/SOURCES.txt
pylmkit.egg-info/dependency_links.txt
pylmkit.egg-info/requires.txt
pylmkit.egg-info/top_level.txt
pylmkit/app/__init__.py
pylmkit/app/chatdb.py
pylmkit/app/rag.py
pylmkit/app/roleplay.py
pylmkit/app/summary.py
pylmkit/core/__init__.py
pylmkit/core/base.py
pylmkit/core/flow.py
pylmkit/core/html.py
pylmkit/core/prompt.py
pylmkit/llms/__init__.py
pylmkit/llms/_huggingface_llm.py
pylmkit/llms/_spark.py
pylmkit/llms/_zhipu.py
pylmkit/memory/__init__.py
pylmkit/memory/common.py
pylmkit/perception/__init__.py
pylmkit/perception/directory.py
pylmkit/perception/text.py
pylmkit/tools/__init__.py
pylmkit/tools/action.py
pylmkit/tools/common.py
pylmkit/tools/executor.py
pylmkit/tools/kit.py
pylmkit/tools/parse.py
pylmkit/tools/search.py
pylmkit/utils/__init__.py
pylmkit/utils/data_utils.py
pylmkit/utils/sql_base.py
pylmkit/web/__init__.py
pylmkit/web/webui.py
test/test_newllm.py
test/test_rag.py
test/test_roleplay.py