Metadata-Version: 2.1
Name: pylmkit
Version: 0.0.22
Summary: pylmkit: Help users quickly build practical large model applications!
Home-page: https://github.com/52phm/pylmkit
Author: 52phm
Author-email: 2374521450@qq.com
License: Apache License-2.0
Project-URL: Homepage, http://app.pylmkit.cn
Project-URL: Documentation, http://en.pylmkit.cn
Project-URL: 应用主页, http://app.pylmkit.cn
Project-URL: 中文文档, http://zh.pylmkit.cn
License-File: LICENSE
